pydiode/__init__.py
pydiode/analyze_details.py
pydiode/common.py
pydiode/decrypt.py
pydiode/generator.py
pydiode/pydiode.py
pydiode/receive.py
pydiode/send.py
pydiode/tar.py
pydiode/gui/__init__.py
pydiode/gui/common.py
pydiode/gui/main.py
pydiode/gui/receive.py
pydiode/gui/send.py
pydiode-0.0.4.dist-info/METADATA
pydiode-0.0.4.dist-info/WHEEL
pydiode-0.0.4.dist-info/entry_points.txt
pydiode-0.0.4.dist-info/licenses/LICENSE
pydiode-0.0.4.dist-info/RECORD
