Metadata-Version: 2.4
Name: pydiode
Version: 0.0.4
Summary: Transfer data through a unidirectional network (i.e., a data diode)
Project-URL: Homepage, https://github.com/ClarkuCSCI/pydiode
Project-URL: Bug Tracker, https://github.com/ClarkuCSCI/pydiode/issues
Author-email: Peter Story <peter.garth.story@gmail.com>
License-File: LICENSE
Classifier: License :: OSI Approved :: MIT License
Classifier: Operating System :: OS Independent
Classifier: Programming Language :: Python :: 3
Requires-Python: >=3.11
